{
    "Zombie Walker": {
        "checkpoints": [
            {
                "steps": 499978,
                "file_path": "results\\AdrianColTest8\\Zombie Walker\\Zombie Walker-499978.onnx",
                "reward": null,
                "creation_time": 1711126855.8336134,
                "auxillary_file_paths": [
                    "results\\AdrianColTest8\\Zombie Walker\\Zombie Walker-499978.pt"
                ]
            },
            {
                "steps": 999943,
                "file_path": "results\\AdrianColTest8\\Zombie Walker\\Zombie Walker-999943.onnx",
                "reward": null,
                "creation_time": 1711128718.7675962,
                "auxillary_file_paths": [
                    "results\\AdrianColTest8\\Zombie Walker\\Zombie Walker-999943.pt"
                ]
            },
            {
                "steps": 1000007,
                "file_path": "results\\AdrianColTest8\\Zombie Walker\\Zombie Walker-1000007.onnx",
                "reward": null,
                "creation_time": 1711128718.822092,
                "auxillary_file_paths": [
                    "results\\AdrianColTest8\\Zombie Walker\\Zombie Walker-1000007.pt"
                ]
            }
        ],
        "final_checkpoint": {
            "steps": 1000007,
            "file_path": "results\\AdrianColTest8\\Zombie Walker.onnx",
            "reward": null,
            "creation_time": 1711128718.822092,
            "auxillary_file_paths": [
                "results\\AdrianColTest8\\Zombie Walker\\Zombie Walker-1000007.pt"
            ]
        }
    },
    "metadata": {
        "stats_format_version": "0.3.0",
        "mlagents_version": "0.30.0",
        "torch_version": "2.2.1+cpu"
    }
}